scim_cli/__init__.py
scim_cli-0.1.0.dist-info/METADATA
scim_cli-0.1.0.dist-info/WHEEL
scim_cli-0.1.0.dist-info/entry_points.txt
scim_cli-0.1.0.dist-info/RECORD
